Metadata-Version: 2.1
Name: odoo-addon-sale_order_line_sequence
Version: 18.0.1.1.0.5
Requires-Python: >=3.10
Requires-Dist: odoo==18.0.*
Summary: Propagates SO line sequence to invoices and stock picking.
Home-page: https://github.com/OCA/sale-workflow
License: AGPL-3
Author: ForgeFlow, Serpent CS, Odoo Community Association (OCA)
Author-email: support@odoo-community.org
Classifier: Programming Language :: Python
Classifier: Framework :: Odoo
Classifier: Framework :: Odoo :: 18.0
Classifier: License :: OSI Approved :: GNU Affero General Public License v3
